main.py
setup.py
test.py
rfch-2.0.1.dist-info/METADATA
rfch-2.0.1.dist-info/WHEEL
rfch-2.0.1.dist-info/top_level.txt
rfch-2.0.1.dist-info/RECORD
