Metadata-Version: 2.1
Name: rfch
Version: 2.0.1
Summary: serial库rfid模块整合库
Home-page: 
Author: Liu YUchen
Author-email: liuyuchen032901@outlook.com
